nsq/__init__.py
nsq/_compat.py
nsq/async.py
nsq/backoff_timer.py
nsq/client.py
nsq/conn.py
nsq/deflate_socket.py
nsq/event.py
nsq/legacy_reader.py
nsq/message.py
nsq/protocol.py
nsq/reader.py
nsq/snappy_socket.py
nsq/sync.py
nsq/version.py
nsq/writer.py
tests/__init__.py
tests/mock_socket.py
tests/reader_unit_test_helpers.py
tests/test_async.py
tests/test_backoff.py
tests/test_basic.py
tests/test_command.py
tests/test_rdy.py
tests/test_reader.py
tests/test_sync.py
tests/test_writer.py
yeansq-0.0.1.dist-info/AUTHORS
yeansq-0.0.1.dist-info/LICENSE
yeansq-0.0.1.dist-info/METADATA
yeansq-0.0.1.dist-info/WHEEL
yeansq-0.0.1.dist-info/top_level.txt
yeansq-0.0.1.dist-info/RECORD
