Metadata-Version: 2.1
Name: yeansq
Version: 0.0.1
Summary: A package for faster coding.
Home-page: https://github.com/private_repo/nsq
Author: slipper
Author-email: r2fscg@gmail.com
License: UNKNOWN
Platform: UNKNOWN
Classifier: Programming Language :: Python :: 3
Classifier: License :: OSI Approved :: MIT License
Classifier: Operating System :: OS Independent
License-File: LICENSE
License-File: AUTHORS
Requires-Dist: tornado
